sftp_py/__init__.py
sftp_py/transfer.py
sftp_py-0.2.1.dist-info/AUTHORS.md
sftp_py-0.2.1.dist-info/LICENSE
sftp_py-0.2.1.dist-info/METADATA
sftp_py-0.2.1.dist-info/WHEEL
sftp_py-0.2.1.dist-info/top_level.txt
sftp_py-0.2.1.dist-info/RECORD
