Metadata-Version: 2.1
Name: sftp-py
Version: 0.2.1
Summary: py_sftp uses sftp to transfer files from remote to local and vice-versa.
Home-page: https://github.com/AlexOrlek/sftp_py
Author: Alex Orlek
Author-email: alex.orlek@gmail.com
License: MIT license
Keywords: sftp_py
Platform: UNKNOWN
Classifier: Development Status :: 2 - Pre-Alpha
Classifier: Intended Audience :: Developers
Classifier: License :: OSI Approved :: MIT License
Classifier: Natural Language :: English
Classifier: Programming Language :: Python :: 3
Classifier: Programming Language :: Python :: 3.4
Classifier: Programming Language :: Python :: 3.5
Classifier: Programming Language :: Python :: 3.6
Classifier: Programming Language :: Python :: 3.7
Classifier: Programming Language :: Python :: 3.8
Classifier: Programming Language :: Python :: 3.9
Requires-Python: >=3.4
Requires-Dist: paramiko (>=2.7.1)
